[{"Phone number":"0887862237","Service Charge":65.52},{"Phone number":"0815909438","Service Charge":116.95},{"Phone number":"0839200962","Service Charge":93.37},{"Phone number":"0831596076","Service Charge":11.23},{"Phone number":"0885620697","Service Charge":106.83},{"Phone number":"0867266297","Service Charge":114.02},{"Phone number":"0859560816","Service Charge":23.02},{"Phone number":"0888027637","Service Charge":32.27},{"Phone number":"0898267749","Service Charge":86.83},{"Phone number":"0887563471","Service Charge":65.05},{"Phone number":"0844994279","Service Charge":66.17},{"Phone number":"0840014668","Service Charge":107.93},{"Phone number":"0886387134","Service Charge":5.35},{"Phone number":"0882913422","Service Charge":95.02},{"Phone number":"0883961304","Service Charge":78.58},{"Phone number":"0806241221","Service Charge":3.0},{"Phone number":"0877573105","Service Charge":109.13},{"Phone number":"0857522134","Service Charge":118.27},{"Phone number":"0866407778","Service Charge":113.42},{"Phone number":"0874640178","Service Charge":80.77},{"Phone number":"0849639708","Service Charge":39.72},{"Phone number":"0825653143","Service Charge":34.8},{"Phone number":"0800531748","Service Charge":111.18},{"Phone number":"0859890390","Service Charge":91.6},{"Phone number":"0857920882","Service Charge":79.88},{"Phone number":"0816160625","Service Charge":61.3},{"Phone number":"0829419831","Service Charge":28.67},{"Phone number":"0821734732","Service Charge":8.82},{"Phone number":"0848619041","Service Charge":7.62},{"Phone number":"0849989754","Service Charge":53.18},{"Phone number":"0878013300","Service Charge":29.2},{"Phone number":"0856874944","Service Charge":30.43},{"Phone number":"0832796119","Service Charge":113.42},{"Phone number":"0852148687","Service Charge":99.25},{"Phone number":"0811063879","Service Charge":104.02},{"Phone number":"0855443773","Service Charge":3.0},{"Phone number":"0865035767","Service Charge":78.32},{"Phone number":"0865971491","Service Charge":106.38},{"Phone number":"0802888109","Service Charge":37.55},{"Phone number":"0829537878","Service Charge":26.08},{"Phone number":"0845110465","Service Charge":21.05},{"Phone number":"0828132696","Service Charge":90.9},{"Phone number":"0882216341","Service Charge":33.15},{"Phone number":"0848000319","Service Charge":70.2},{"Phone number":"0851378914","Service Charge":20.08},{"Phone number":"0872452331","Service Charge":63.35},{"Phone number":"0883362043","Service Charge":87.53},{"Phone number":"0812554758","Service Charge":7.85},{"Phone number":"0896271774","Service Charge":24.9},{"Phone number":"0834259317","Service Charge":71.68},{"Phone number":"0823331753","Service Charge":118.5},{"Phone number":"0883738595","Service Charge":22.18},{"Phone number":"0838858658","Service Charge":120.47},{"Phone number":"0806878293","Service Charge":22.7},{"Phone number":"0881984147","Service Charge":79.12},{"Phone number":"0806220212","Service Charge":71.18},{"Phone number":"0827994482","Service Charge":15.47},{"Phone number":"0888217204","Service Charge":112.98},{"Phone number":"0802458583","Service Charge":75.68},{"Phone number":"0897481358","Service Charge":62.45},{"Phone number":"0843109748","Service Charge":117.93},{"Phone number":"0850565674","Service Charge":96.77},{"Phone number":"0808051798","Service Charge":83.08},{"Phone number":"0887141459","Service Charge":103.8},{"Phone number":"0802931979","Service Charge":44.27},{"Phone number":"0821311309","Service Charge":94.08},{"Phone number":"0881295913","Service Charge":115.18},{"Phone number":"0841119653","Service Charge":72.73},{"Phone number":"0811140735","Service Charge":11.85},{"Phone number":"0852428745","Service Charge":80.8},{"Phone number":"0856439274","Service Charge":110.23},{"Phone number":"0861833155","Service Charge":100.03},{"Phone number":"0810660431","Service Charge":21.03},{"Phone number":"0867308013","Service Charge":45.78},{"Phone number":"0849958685","Service Charge":31.95},{"Phone number":"0821473408","Service Charge":17.78},{"Phone number":"0869421388","Service Charge":21.3},{"Phone number":"0882659114","Service Charge":70.53},{"Phone number":"0817220593","Service Charge":82.18},{"Phone number":"0889550199","Service Charge":106.43},{"Phone number":"0848779172","Service Charge":57.5},{"Phone number":"0845349237","Service Charge":7.5},{"Phone number":"0800524835","Service Charge":41.68},{"Phone number":"0892780969","Service Charge":108.57},{"Phone number":"0822509201","Service Charge":94.82},{"Phone number":"0867950067","Service Charge":58.83},{"Phone number":"0803704073","Service Charge":113.12},{"Phone number":"0833873084","Service Charge":58.18},{"Phone number":"0863822130","Service Charge":85.73},{"Phone number":"0857529418","Service Charge":88.87},{"Phone number":"0856806067","Service Charge":84.03},{"Phone number":"0814528728","Service Charge":61.95},{"Phone number":"0877238659","Service Charge":78.75},{"Phone number":"0825301901","Service Charge":52.78},{"Phone number":"0889989684","Service Charge":85.73},{"Phone number":"0898252328","Service Charge":74.45},{"Phone number":"0844786544","Service Charge":76.43},{"Phone number":"0832528332","Service Charge":18.1},{"Phone number":"0882860039","Service Charge":73.87},{"Phone number":"0833497075","Service Charge":103.53}]